[
    {
        "id": 1,
        "nombre": "Pelé",
        "pais": "Brasil",
        "fecha_nacimiento": "23/10/1940",
        "continente": "Sudamérica",
        "posicion": "Delantero",
        "titulos": 25,
        "dorsal": 10,
        "equipo_iconico": "Santos FC",
        "imagen": "images/pele.webp"
    },
    {
        "id": 2,
        "nombre": "Diego Maradona",
        "pais": "Argentina",
        "fecha_nacimiento": "30/10/1960",
        "continente": "Sudamérica",
        "posicion": "Mediocampista",
        "titulos": 11,
        "dorsal": 10,
        "equipo_iconico": "Napoli",
        "imagen": "images/el-diego.jpg"
    },
    {
        "id": 3,
        "nombre": "Lionel Messi",
        "pais": "Argentina",
        "fecha_nacimiento": "24/06/1987",
        "continente": "Sudamérica",
        "posicion": "Delantero",
        "titulos": 46,
        "dorsal": 10,
        "equipo_iconico": "FC Barcelona",
        "imagen": "images/el-goat.jpg"
    },
    {
        "id": 4,
        "nombre": "Cristiano Ronaldo",
        "pais": "Portugal",
        "fecha_nacimiento": "05/02/1985",
        "continente": "Europa",
        "posicion": "Delantero",
        "titulos": 35,
        "dorsal": 7,
        "equipo_iconico": "Real Madrid",
        "imagen": "images/el-bicho.jpg"
    },
    {
        "id": 5,
        "nombre": "Zinedine Zidane",
        "pais": "Francia",
        "fecha_nacimiento": "23/06/1972",
        "continente": "Europa",
        "posicion": "Mediocampista",
        "titulos": 14,
        "dorsal": 10,
        "equipo_iconico": "Real Madrid",
        "imagen": "images/el-mago.jpg"
    },
    {
        "id": 6,
        "nombre": "Ronaldinho",
        "pais": "Brasil",
        "fecha_nacimiento": "21/03/1980",
        "continente": "Sudamérica",
        "posicion": "Delantero",
        "titulos": 18,
        "dorsal": 10,
        "equipo_iconico": "FC Barcelona",
        "imagen": "images/dinho.jpg"
    },
    {
        "id": 7,
        "nombre": "Andrés Iniesta",
        "pais": "España",
        "fecha_nacimiento": "11/05/1984",
        "continente": "Europa",
        "posicion": "Mediocampista",
        "titulos": 39,
        "dorsal": 8,
        "equipo_iconico": "FC Barcelona",
        "imagen": "images/iniesta.jpg"
    },
    {
        "id": 8,
        "nombre": "Ronaldo Nazário",
        "pais": "Brasil",
        "fecha_nacimiento": "22/09/1976",
        "continente": "Sudamérica",
        "posicion": "Delantero",
        "titulos": 18,
        "dorsal": 9,
        "equipo_iconico": "Real Madrid",
        "imagen": "images/el-fenomeno.jpg"
    },
    {
        "id": 9,
        "nombre": "Xavi Hernández",
        "pais": "España",
        "fecha_nacimiento": "25/01/1980",
        "continente": "Europa",
        "posicion": "Mediocampista",
        "titulos": 33,
        "dorsal": 6,
        "equipo_iconico": "FC Barcelona",
        "imagen": "images/xavi.jpeg"
    },
    {
        "id": 10,
        "nombre": "Roberto Baggio",
        "pais": "Italia",
        "fecha_nacimiento": "18/02/1967",
        "continente": "Europa",
        "posicion": "Delantero",
        "titulos": 7,
        "dorsal": 10,
        "equipo_iconico": "Fiorentina",
        "imagen": "images/baggio.jpg"
    },
    {
        "id": 11,
        "nombre": "KAKA",
        "pais": "Brasil",
        "fecha_nacimiento": "22/04/1981",
        "continente": "Sudamérica",
        "posicion": "Centrocampista, Mediapunta",
        "titulos": 10,
        "dorsal": 22,
        "equipo_iconico": "AC Milan",
        "imagen": "images/kaka.jpg"
    },
    {
        "id": 12,
        "nombre": "Johan Cruyff",
        "pais": "Países Bajos",
        "fecha_nacimiento": "25/04/1947",
        "continente": "Europa",
        "posicion": "Delantero",
        "titulos": 20,
        "dorsal": 14,
        "equipo_iconico": "Ajax",
        "imagen": "images/cruyff.jpg"
    },
    {
        "id": 13,
        "nombre": "Neymar Jr.",
        "pais": "Brasil",
        "fecha_nacimiento": "05/02/1992",
        "continente": "Sudamérica",
        "posicion": "Delantero",
        "titulos": 30,
        "dorsal": 10,
        "equipo_iconico": "FC Barcelona",
        "imagen": "images/ney.webp"
    },
    {
        "id": 14,
        "nombre": "Franz Beckenbauer",
        "pais": "Alemania",
        "fecha_nacimiento": "11/09/1945",
        "continente": "Europa",
        "posicion": "Defensa",
        "titulos": 17,
        "dorsal": 5,
        "equipo_iconico": "Bayern Múnich",
        "imagen": "images/el-kaiser.jpg"
    },
    {
        "id": 15,
        "nombre": "Roberto Carlos",
        "pais": "Brasil",
        "fecha_nacimiento": "10/04/1973",
        "continente": "Sudamérica",
        "posicion": "Defensa",
        "titulos": 20,
        "dorsal": 3,
        "equipo_iconico": "Real Madrid",
        "imagen": "images/el-misil.jpg"
    },
    {
        "id": 16,
        "nombre": "Paolo Maldini",
        "pais": "Italia",
        "fecha_nacimiento": "26/06/1968",
        "continente": "Europa",
        "posicion": "Defensa",
        "titulos": 26,
        "dorsal": 3,
        "equipo_iconico": "AC Milan",
        "imagen": "images/maldini.jpg"
    },
    {
        "id": 17,
        "nombre": "Lev Yashin",
        "pais": "Rusia",
        "fecha_nacimiento": "22/10/1929",
        "continente": "Europa",
        "posicion": "Portero",
        "titulos": 10,
        "dorsal": 1,
        "equipo_iconico": "Dínamo Moscú",
        "imagen": "images/la-araña.jpg"
    },
    {
        "id": 18,
        "nombre": "Gianluigi Buffon",
        "pais": "Italia",
        "fecha_nacimiento": "28/01/1978",
        "continente": "Europa",
        "posicion": "Portero",
        "titulos": 28,
        "dorsal": 1,
        "equipo_iconico": "Juventus",
        "imagen": "images/buffon.jpg"
    },
    {
        "id": 19,
        "nombre": "Iker Casillas",
        "pais": "España",
        "fecha_nacimiento": "20/05/1981",
        "continente": "Europa",
        "posicion": "Portero",
        "titulos": 19,
        "dorsal": 1,
        "equipo_iconico": "Real Madrid",
        "imagen": "images/casillas.jpg"
    },
    {
        "id": 20,
        "nombre": "Manuel Neuer",
        "pais": "Alemania",
        "fecha_nacimiento": "27/03/1986",
        "continente": "Europa",
        "posicion": "Portero",
        "titulos": 30,
        "dorsal": 1,
        "equipo_iconico": "Bayern Múnich",
        "imagen": "images/neuer.jpg"
    }
]